Metadata-Version: 2.1
Name: tsclassification
Version: 1.0.1
Summary: A shapelet classifier for time series data.
Home-page: https://github.com/gellison321/tsclassification
Author: Grant Ellison
Author-email: gellison321@gmail.com
License: UNKNOWN
Download-URL: https://github.com/gellison321/tsclassification/archive/refs/tags/1.0.1.tar.gz
Keywords: timeseries,data science,data analysis,classificaiton,machine learning
Platform: UNKNOWN
Classifier: Development Status :: 4 - Beta
Classifier: Intended Audience :: Developers
Classifier: Intended Audience :: Science/Research
Classifier: Topic :: Software Development :: Build Tools
Classifier: Operating System :: OS Independent
Classifier: License :: OSI Approved :: MIT License
Classifier: Programming Language :: Python
Classifier: Programming Language :: Python :: 3.8
Classifier: Programming Language :: Python :: 3.9
License-File: LICENSE
